setup.py
probe_plotting2/__init__.py
probe_plotting2/plotting.py
probe_plotting2.egg-info/PKG-INFO
probe_plotting2.egg-info/SOURCES.txt
probe_plotting2.egg-info/dependency_links.txt
probe_plotting2.egg-info/entry_points.txt
probe_plotting2.egg-info/requires.txt
probe_plotting2.egg-info/top_level.txt
probe_plotting2.egg-info/zip-safe