Metadata-Version: 1.0
Name: probe-plotting2
Version: 0.0.1
Summary: Helper functions to deal with matplotlib.
Home-page: UNKNOWN
Author: Petr Zikan
Author-email: zikan.p@gmail.com
License: GPLv3
Platform: UNKNOWN
